gitlabcicli/__init__.py
gitlabcicli/__main__.py
gitlabcicli/gitlabapiwrapper.py
gitlabcicli/gitlabcicli.py
gitlabcicli/gitwrapper.py
gitlabcicli/keyring_wrapper.py
gitlabcicli/script_helpers.py
gitlabcicli/utils.py
gitlabcicli-0.2.6.dist-info/LICENSE
gitlabcicli-0.2.6.dist-info/METADATA
gitlabcicli-0.2.6.dist-info/WHEEL
gitlabcicli-0.2.6.dist-info/entry_points.txt
gitlabcicli-0.2.6.dist-info/RECORD
